Bgolearn/BGOsampling.py
Bgolearn/__init__.py
Bgolearn/BgolearnFuns/BGO_eval.py
Bgolearn/BgolearnFuns/BGOclf.py
Bgolearn/BgolearnFuns/BGOmax.py
Bgolearn/BgolearnFuns/BGOmin.py
Bgolearn/BgolearnFuns/__init__.py
bgolearn-3.0.0.dist-info/METADATA
bgolearn-3.0.0.dist-info/WHEEL
bgolearn-3.0.0.dist-info/top_level.txt
bgolearn-3.0.0.dist-info/RECORD
