Metadata-Version: 2.4
Name: Bgolearn
Version: 3.0.0
Summary: A Bayesian global optimization package for material design
Home-page: https://github.com/Bin-Cao/Bgolearn
Author: CaoBin
Author-email: bcao686@connect.hkust-gz.edu.cn
Maintainer: CaoBin
Maintainer-email: bcao686@connect.hkust-gz.edu.cn
License: MIT License
Classifier: Development Status :: 3 - Alpha
Classifier: Intended Audience :: Developers
Classifier: Topic :: Software Development :: Build Tools
Classifier: License :: OSI Approved :: MIT License
Classifier: Programming Language :: Python :: 3
Requires-Python: >=3.7
Requires-Dist: scipy
Requires-Dist: scikit-learn
Requires-Dist: pandas
Requires-Dist: numpy
Requires-Dist: matplotlib
Requires-Dist: multiprocess
Requires-Dist: art
Dynamic: author
Dynamic: author-email
Dynamic: classifier
Dynamic: description
Dynamic: home-page
Dynamic: license
Dynamic: maintainer
Dynamic: maintainer-email
Dynamic: requires-dist
Dynamic: requires-python
Dynamic: summary
